[
    {
        "title": "Dashboard",
        "icon": "bi-gear-fill",
        "childrens": [
            {
                "title": "Home",
                "icon": "bi-house-fill",
                "path": "/"
            },
            {
                "title": "About",
                "icon": "bi-info-circle-fill",
                "path": "/about"
            },
            {
                "title": "Contact",
                "icon": "bi-phone-fill",
                "childrens": [
                    {
                        "title": "Facebook",
                        "icon": "bi-facebook"
                    },
                    {
                        "title": "Twitter",
                        "icon": "bi-twitter"
                    },
                    {
                        "title": "Instagram",
                        "icon": "bi-instagram"
                    }
                ]
            },
            {
                "title": "FAQ",
                "icon": "bi-question-circle-fill"
            }
        ]
    },
    {
        "title": "Create",
        "icon": "bi-info-circle-fill",
        "childrens": [
            {
                "title": "New expense",
                "path": "/expense"
            },
            {
                "title": "Extra-Income",
                "path": "/extra-income"
            },
            {
                "title": "Damaged-Product",
                "path": "/damaged-good"
            },
            {
                "title": "Reset Password",
                "path": "/reset-password"
            }
        ]
    },
    {
        "title": "Category",
        "icon": "bi-person-fill",
        "childrens": [
            {
                "title": "expense",
                "path": "/expense"
            },
            {
                "title": "extra-income",
                "path": "/income-extra"
            },
            {
                "title": "measurment",
                "path": "/measurment"
            },
            {
                "title": "Brand",
                "path": "/brand"
            },
            {
                "title": "Color",
                "path": "/color"
            },
            {
                "title": "Settings",
                "childrens": [
                    {
                        "title": "Account",
                        "path": "/settings/account"
                    },
                    {
                        "title": "Billing",
                        "childrens": [
                            {
                                "title": "Payment",
                                "path": "/settings/billing/payment"
                            },
                            {
                                "title": "Subscription",
                                "path": "/settings/billing/subscription"
                            }
                        ]
                    },
                    {
                        "title": "Notifications",
                        "path": "/settings/notifications"
                    }
                ]
            },
            {
                "title": "Logout",
                "path": "/logout"
            }
        ]
    },
    {
        "title": "Advance",
        "icon": "bi-view-list",
        "childrens": [
            {
                "title": "Search",
                "path": "/search"
            },
            {
                "title": "History",
                "path": "/history"   
            }
        ]
    },
    {
        "title": "Support",
        "icon": "bi-question-circle-fill",
        "path": "/support"
    },
    {
        "title": "Report Bug",
        "icon": "bi-bug",
        "path": "/report-bug"
    }
]
